{
	"backtraceGraph" : 
	{
		"commands" : 
		[
			"install"
		],
		"files" : 
		[
			"OpenCC/data/CMakeLists.txt"
		],
		"nodes" : 
		[
			{
				"file" : 0
			},
			{
				"command" : 0,
				"file" : 0,
				"line" : 150,
				"parent" : 0
			},
			{
				"command" : 0,
				"file" : 0,
				"line" : 150,
				"parent" : 0
			},
			{
				"command" : 0,
				"file" : 0,
				"line" : 150,
				"parent" : 0
			},
			{
				"command" : 0,
				"file" : 0,
				"line" : 150,
				"parent" : 0
			},
			{
				"command" : 0,
				"file" : 0,
				"line" : 150,
				"parent" : 0
			},
			{
				"command" : 0,
				"file" : 0,
				"line" : 150,
				"parent" : 0
			},
			{
				"command" : 0,
				"file" : 0,
				"line" : 150,
				"parent" : 0
			},
			{
				"command" : 0,
				"file" : 0,
				"line" : 150,
				"parent" : 0
			},
			{
				"command" : 0,
				"file" : 0,
				"line" : 150,
				"parent" : 0
			},
			{
				"command" : 0,
				"file" : 0,
				"line" : 150,
				"parent" : 0
			},
			{
				"command" : 0,
				"file" : 0,
				"line" : 150,
				"parent" : 0
			},
			{
				"command" : 0,
				"file" : 0,
				"line" : 150,
				"parent" : 0
			},
			{
				"command" : 0,
				"file" : 0,
				"line" : 150,
				"parent" : 0
			},
			{
				"command" : 0,
				"file" : 0,
				"line" : 150,
				"parent" : 0
			},
			{
				"command" : 0,
				"file" : 0,
				"line" : 150,
				"parent" : 0
			},
			{
				"command" : 0,
				"file" : 0,
				"line" : 150,
				"parent" : 0
			},
			{
				"command" : 0,
				"file" : 0,
				"line" : 181,
				"parent" : 0
			}
		]
	},
	"installers" : 
	[
		{
			"backtrace" : 1,
			"component" : "Unspecified",
			"destination" : "/usr/local/share/opencc",
			"paths" : 
			[
				"build/unknown-Release/OpenCC/data/STCharacters.ocd2"
			],
			"type" : "file"
		},
		{
			"backtrace" : 2,
			"component" : "Unspecified",
			"destination" : "/usr/local/share/opencc",
			"paths" : 
			[
				"build/unknown-Release/OpenCC/data/STPhrases.ocd2"
			],
			"type" : "file"
		},
		{
			"backtrace" : 3,
			"component" : "Unspecified",
			"destination" : "/usr/local/share/opencc",
			"paths" : 
			[
				"build/unknown-Release/OpenCC/data/TSCharacters.ocd2"
			],
			"type" : "file"
		},
		{
			"backtrace" : 4,
			"component" : "Unspecified",
			"destination" : "/usr/local/share/opencc",
			"paths" : 
			[
				"build/unknown-Release/OpenCC/data/TSPhrases.ocd2"
			],
			"type" : "file"
		},
		{
			"backtrace" : 5,
			"component" : "Unspecified",
			"destination" : "/usr/local/share/opencc",
			"paths" : 
			[
				"build/unknown-Release/OpenCC/data/TWVariants.ocd2"
			],
			"type" : "file"
		},
		{
			"backtrace" : 6,
			"component" : "Unspecified",
			"destination" : "/usr/local/share/opencc",
			"paths" : 
			[
				"build/unknown-Release/OpenCC/data/TWVariantsRevPhrases.ocd2"
			],
			"type" : "file"
		},
		{
			"backtrace" : 7,
			"component" : "Unspecified",
			"destination" : "/usr/local/share/opencc",
			"paths" : 
			[
				"build/unknown-Release/OpenCC/data/HKVariants.ocd2"
			],
			"type" : "file"
		},
		{
			"backtrace" : 8,
			"component" : "Unspecified",
			"destination" : "/usr/local/share/opencc",
			"paths" : 
			[
				"build/unknown-Release/OpenCC/data/HKVariantsRevPhrases.ocd2"
			],
			"type" : "file"
		},
		{
			"backtrace" : 9,
			"component" : "Unspecified",
			"destination" : "/usr/local/share/opencc",
			"paths" : 
			[
				"build/unknown-Release/OpenCC/data/JPVariants.ocd2"
			],
			"type" : "file"
		},
		{
			"backtrace" : 10,
			"component" : "Unspecified",
			"destination" : "/usr/local/share/opencc",
			"paths" : 
			[
				"build/unknown-Release/OpenCC/data/JPShinjitaiCharacters.ocd2"
			],
			"type" : "file"
		},
		{
			"backtrace" : 11,
			"component" : "Unspecified",
			"destination" : "/usr/local/share/opencc",
			"paths" : 
			[
				"build/unknown-Release/OpenCC/data/JPShinjitaiPhrases.ocd2"
			],
			"type" : "file"
		},
		{
			"backtrace" : 12,
			"component" : "Unspecified",
			"destination" : "/usr/local/share/opencc",
			"paths" : 
			[
				"build/unknown-Release/OpenCC/data/TWPhrases.ocd2"
			],
			"type" : "file"
		},
		{
			"backtrace" : 13,
			"component" : "Unspecified",
			"destination" : "/usr/local/share/opencc",
			"paths" : 
			[
				"build/unknown-Release/OpenCC/data/TWPhrasesRev.ocd2"
			],
			"type" : "file"
		},
		{
			"backtrace" : 14,
			"component" : "Unspecified",
			"destination" : "/usr/local/share/opencc",
			"paths" : 
			[
				"build/unknown-Release/OpenCC/data/TWVariantsRev.ocd2"
			],
			"type" : "file"
		},
		{
			"backtrace" : 15,
			"component" : "Unspecified",
			"destination" : "/usr/local/share/opencc",
			"paths" : 
			[
				"build/unknown-Release/OpenCC/data/HKVariantsRev.ocd2"
			],
			"type" : "file"
		},
		{
			"backtrace" : 16,
			"component" : "Unspecified",
			"destination" : "/usr/local/share/opencc",
			"paths" : 
			[
				"build/unknown-Release/OpenCC/data/JPVariantsRev.ocd2"
			],
			"type" : "file"
		},
		{
			"backtrace" : 17,
			"component" : "Unspecified",
			"destination" : "/usr/local/share/opencc",
			"paths" : 
			[
				"OpenCC/data/config/hk2s.json",
				"OpenCC/data/config/hk2t.json",
				"OpenCC/data/config/jp2t.json",
				"OpenCC/data/config/s2hk.json",
				"OpenCC/data/config/s2t.json",
				"OpenCC/data/config/s2tw.json",
				"OpenCC/data/config/s2twp.json",
				"OpenCC/data/config/t2hk.json",
				"OpenCC/data/config/t2jp.json",
				"OpenCC/data/config/t2s.json",
				"OpenCC/data/config/t2tw.json",
				"OpenCC/data/config/tw2s.json",
				"OpenCC/data/config/tw2sp.json",
				"OpenCC/data/config/tw2t.json"
			],
			"type" : "file"
		}
	],
	"paths" : 
	{
		"build" : "OpenCC/data",
		"source" : "OpenCC/data"
	}
}
